zccypkg/__init__.py
zccypkg/main.py
zccypkg-0.0.3.dist-info/METADATA
zccypkg-0.0.3.dist-info/WHEEL
zccypkg-0.0.3.dist-info/RECORD
