Metadata-Version: 2.1
Name: zccypkg
Version: 0.0.3
Summary: First pypi library
License: MIT
Author: Kenny James
Author-email: info@zone-connect.com
Requires-Python: >=3.12,<4.0
Classifier: License :: OSI Approved :: MIT License
Classifier: Programming Language :: Python :: 3
Classifier: Programming Language :: Python :: 3.12
Classifier: Programming Language :: Python :: 3.13
